_maus_version.py
maus/__init__.py
maus/cli.py
maus/division_helper.py
maus/edifact.py
maus/maus_provider.py
maus/mig_ahb_matching.py
maus/navigation.py
maus/py.typed
maus/transformation.py
maus/models/__init__.py
maus/models/anwendungshandbuch.py
maus/models/edifact_components.py
maus/models/message_implementation_guide.py
maus/reader/__init__.py
maus/reader/ahb_location_xml.py
maus/reader/etree_element_helpers.py
maus/reader/flat_ahb_reader.py
maus/reader/mig_ahb_name_helpers.py
maus/reader/mig_reader.py
maus/reader/mig_xml_reader.py
maus/reader/tree_to_sgh.py
maus-0.6.1.dist-info/METADATA
maus-0.6.1.dist-info/WHEEL
maus-0.6.1.dist-info/entry_points.txt
maus-0.6.1.dist-info/licenses/LICENSE
maus-0.6.1.dist-info/RECORD
