Metadata-Version: 2.3
Name: maus
Version: 0.6.1
Summary: Python Library that consolidates Anwendungshandbücher (AHB) and Message Implementation Guides (MIG)
Project-URL: Changelog, https://github.com/Hochfrequenz/mig_ahb_utility_stack/releases
Project-URL: Homepage, https://github.com/Hochfrequenz/mig_ahb_utility_stack
Project-URL: Documentation, https://maus.readthedocs.io/en/latest/
Author-email: Hochfrequenz Unternehmensberatung GmbH <info@hochfrequenz.de>
License: MIT
License-File: LICENSE
Keywords: AHB,MIG,edi@energy,maus
Classifier: Development Status :: 4 - Beta
Classifier: Environment :: Console
Classifier: Intended Audience :: Developers
Classifier: License :: OSI Approved :: MIT License
Classifier: Operating System :: OS Independent
Classifier: Programming Language :: Python
Classifier: Programming Language :: Python :: 3 :: Only
Classifier: Programming Language :: Python :: 3.11
Classifier: Programming Language :: Python :: 3.12
Requires-Python: >=3.8
Requires-Dist: attrs>=22.1.0
Requires-Dist: efoli>=0.0.3
Requires-Dist: marshmallow>=3.18.0
Requires-Dist: more-itertools
Provides-Extra: build-executable
Requires-Dist: pyinstaller==6.10.0; extra == 'build-executable'
Provides-Extra: cli
Requires-Dist: click; extra == 'cli'
Provides-Extra: coverage
Requires-Dist: coverage==7.6.1; extra == 'coverage'
Provides-Extra: dev
Requires-Dist: pip-tools; extra == 'dev'
Provides-Extra: docs
Requires-Dist: sphinx-rtd-theme==2.0.0; extra == 'docs'
Requires-Dist: sphinx==7.4.7; extra == 'docs'
Provides-Extra: formating
Requires-Dist: black==24.8.0; extra == 'formating'
Requires-Dist: isort==5.13.2; extra == 'formating'
Provides-Extra: formatting
Requires-Dist: black==24.8.0; extra == 'formatting'
Requires-Dist: isort==5.13.2; extra == 'formatting'
Provides-Extra: integration-tests
Requires-Dist: pytest-datafiles==3.0.0; extra == 'integration-tests'
Requires-Dist: pytest==8.3.2; extra == 'integration-tests'
Provides-Extra: json-schema
Requires-Dist: marshmallow-jsonschema==0.13.0; extra == 'json-schema'
Provides-Extra: linting
Requires-Dist: pylint==3.2.7; extra == 'linting'
Provides-Extra: packaging
Requires-Dist: build==1.2.2; extra == 'packaging'
Requires-Dist: twine==5.1.1; extra == 'packaging'
Provides-Extra: spell-check
Requires-Dist: codespell==2.3.0; extra == 'spell-check'
Provides-Extra: test-packaging
Requires-Dist: build==1.2.1; extra == 'test-packaging'
Requires-Dist: twine==5.1.1; extra == 'test-packaging'
Provides-Extra: tree
Requires-Dist: lark>=1.1.5; extra == 'tree'
Provides-Extra: type-check
Requires-Dist: mypy==1.11.2; extra == 'type-check'
Requires-Dist: types-xmltodict==0.13.0.3; extra == 'type-check'
Provides-Extra: unit-tests
Requires-Dist: jsonpath-ng==1.6.1; extra == 'unit-tests'
Requires-Dist: pytest-asyncio==0.23.8; extra == 'unit-tests'
Requires-Dist: pytest-datafiles==3.0.0; extra == 'unit-tests'
Requires-Dist: pytest==8.3.2; extra == 'unit-tests'
Provides-Extra: xml
Requires-Dist: lxml>=4.9.2; extra == 'xml'
Requires-Dist: xmltodict; extra == 'xml'
